[
  {
    "t": "10:139:1:s,10:210:1:f,10:313:1:s,0:515:3,0:530:3,8:730:69,6:861:10,12:934:1,3:1428:1,1:1607:3,1:1622:3,9:1832:83,7:1923:10,15:2003:1",
    "s": "great passing|slow intake|center lane",
    "b": [0, 62],
    "d": [6, "2374", "Avery"],
    "p": [0.726592, 0.759827],
    "ft": [0]
  },
  {
    "t": "0:480:2,0:510:2,8:760:44,3:1410:1,1:1590:3,1:1660:3",
    "s": "good auto|ok defense|left lane",
    "b": [0, 55],
    "d": [6, "5937", "Noah"],
    "p": [0.6482, 0.6021],
    "ft": [0]
  },
  {
    "0": 24,
    "1": 33,
    "2": 0,
    "3": 0,
    "4": 0,
    "5": 0,
    "6": 12,
    "7": 9,
    "8": 0,
    "9": 0,
    "10": 0,
    "11": 0,
    "12": 2,
    "13": 0,
    "14": 0,
    "15": 1,
    "16": false,
    "17": "good stuff",
    "18": "bad stuff",
    "19": "idk bro",
    "20": 50,
    "10.s": 2,
    "11.s": 0,
    "10.f": 1,
    "11.f": 0,
    "match": 4,
    "team": "5937",
    "scouter": "daw",
    "p": [0.388082, 0.650504],
    "ft": [0]
  },
  {
    "0": 10,
    "1": 16,
    "2": 1,
    "3": 2,
    "4": 0,
    "5": 0,
    "6": 4,
    "7": 8,
    "8": 0,
    "9": 0,
    "10": 1,
    "11": 1,
    "12": 1,
    "13": 0,
    "14": 0,
    "15": 1,
    "16": true,
    "17": "fast but bricked once",
    "18": "unstable drivetrain",
    "19": "source side",
    "20": 41,
    "10.s": 1,
    "11.s": 1,
    "10.f": 1,
    "11.f": 0,
    "match": 8,
    "team": "9600",
    "scouter": "Lena",
    "p": [0.5123, 0.4777],
    "ft": [0]
  },
  {
    "t": "10:145:1:s,10:201:1:s,0:489:3,0:506:3,6:790:7,3:1502:1,1:1628:3,1:1681:3,1:1722:3,7:1951:9",
    "s": "strong cycle pace|late climb|right wing",
    "b": [0, 67],
    "d": [8, "3663", "Mia"],
    "p": [0.5812, 0.541],
    "ft": [0]
  }
]
